[
    {
        "title": "pad.envs.net",
        "url": "https://pad.envs.net",
        "description": "envs.net is a minimalist, non-commercial shared unix system and will always be free to use.",
        "location": "Germany"
    },
    {
        "title": "pads.c3w.at",
        "url": "https://pads.c3w.at",
        "location": "Austria",
        "_description": "This is an independent community instance of CryptPad."
    },
    {
        "title": "pad.tchncs.de",
        "url": "https://pad.tchncs.de",
        "location": "Germany",
        "description": "The CryptPad instance of tchncs.de – offering a fair amount of storage while trying not to conflict with the official offering."
    },
    {
        "title": "pad.freifunk.duesseldorf.de",
        "url": "https://pad.freifunk.duesseldorf.de",
        "location": "Germany"
    },
    {
        "title": "pad.artemislena.eu",
        "url": "https://pad.artemislena.eu",
        "location": "Germany",
        "description": "Be crime do gay"
    },
    {
        "title": "cryptpad.piratenpartei.de",
        "url": "https://cryptpad.piratenpartei.de",
        "location": "Deutschland",
        "description": "This CryptPad instance is hosted by the Pirate Party of Germany. We stand for privacy and digital sovereignty."
    },
    {
        "title": "cryptpad.cz",
        "url": "https://cryptpad.cz",
        "location": "Czech Republic",
        "description": "This CryptPad instance is hosted by NoLog.cz activist IT collective on our own bare metal servers located in Prague."
    },
    {
        "title": "kumipad.eu",
        "url": "https://kumipad.eu",
        "location": "Austria",
        "description": "A CryptPad instance operated by Kumi Systems."
    },
    {
        "title": "pad.vern.cc",
        "url": "https://pad.vern.cc",
        "location": "a local server in New York, United States",
        "description": "This is the CryptPad instance of ~vern (vern.cc)"
    },
    {
        "title": "Ébauche FACiLe",
        "url": "https://ebauche.facil.services/",
        "location": "Québec",
        "description": "Instance publique de CryptPad opérée par FACiL."
    },
    {
        "title": "NicFab CryptPad",
        "url": "https://cryptpad.nicfab.it",
        "location": "🇮🇹 Italy",
        "description": "It is an independent community instance of CryptPad."
    }
]
