[
    {
        "title": "pad.envs.net",
        "url": "https://pad.envs.net",
        "description": "envs.net is a minimalist, non-commercial shared unix system and will always be free to use.",
        "location": "Germany"
    },
    {
        "title": "pads.c3w.at",
        "url": "https://pads.c3w.at",
        "location": "Austria",
        "_description": "This is an independent community instance of CryptPad."
    },
    {
        "title": "pad.tchncs.de",
        "url": "https://pad.tchncs.de",
        "location": "Germany",
        "description": "CryptPad at tchncs.de"
    },
    {
        "title": "pad.freifunk.duesseldorf.de",
        "url": "https://pad.freifunk.duesseldorf.de",
        "location": "Germany"
    },
    {
        "title": "pad.artemislena.eu",
        "url": "https://pad.artemislena.eu",
        "location": "Germany"
    }
]
